ApacheMina2YonghuZhinan/README.md
ApacheMina2YonghuZhinan/__init__.py
ApacheMina2YonghuZhinan/__main__.py
ApacheMina2YonghuZhinan/file.epub
ApacheMina2YonghuZhinan/index.html
ApacheMina2YonghuZhinan/css/__init__.py
ApacheMina2YonghuZhinan/css/annotations.css
ApacheMina2YonghuZhinan/css/main.css
ApacheMina2YonghuZhinan/css/normalize.css
ApacheMina2YonghuZhinan/css/popup.css
ApacheMina2YonghuZhinan/font/__init__.py
ApacheMina2YonghuZhinan/font/fontello.eot
ApacheMina2YonghuZhinan/font/fontello.svg
ApacheMina2YonghuZhinan/font/fontello.ttf
ApacheMina2YonghuZhinan/font/fontello.woff
ApacheMina2YonghuZhinan/img/__init__.py
ApacheMina2YonghuZhinan/img/annotator-glyph-sprite.png
ApacheMina2YonghuZhinan/img/annotator-icon-sprite.png
ApacheMina2YonghuZhinan/img/apple-touch-icon.png
ApacheMina2YonghuZhinan/img/cancelfullscreen.png
ApacheMina2YonghuZhinan/img/close.png
ApacheMina2YonghuZhinan/img/fullscreen.png
ApacheMina2YonghuZhinan/img/loader.gif
ApacheMina2YonghuZhinan/img/menu-icon.png
ApacheMina2YonghuZhinan/img/save.png
ApacheMina2YonghuZhinan/img/saved.png
ApacheMina2YonghuZhinan/img/settings-s.png
ApacheMina2YonghuZhinan/img/settings.png
ApacheMina2YonghuZhinan/img/star.png
ApacheMina2YonghuZhinan/js/__init__.py
ApacheMina2YonghuZhinan/js/epub.js
ApacheMina2YonghuZhinan/js/epub.min.js
ApacheMina2YonghuZhinan/js/epub.min.map
ApacheMina2YonghuZhinan/js/hooks.min.js
ApacheMina2YonghuZhinan/js/hooks.min.map
ApacheMina2YonghuZhinan/js/reader.js
ApacheMina2YonghuZhinan/js/reader.js.map
ApacheMina2YonghuZhinan/js/reader.min.js
ApacheMina2YonghuZhinan/js/reader.min.map
ApacheMina2YonghuZhinan/js/hooks/__init__.py
ApacheMina2YonghuZhinan/js/hooks/extensions/__init__.py
ApacheMina2YonghuZhinan/js/hooks/extensions/highlight.js
ApacheMina2YonghuZhinan/js/libs/__init__.py
ApacheMina2YonghuZhinan/js/libs/jquery.min.js
ApacheMina2YonghuZhinan/js/libs/localforage.min.js
ApacheMina2YonghuZhinan/js/libs/screenfull.js
ApacheMina2YonghuZhinan/js/libs/screenfull.min.js
apache_mina_2_yonghu_zhinan-2024.2.29.0.dist-info/METADATA
apache_mina_2_yonghu_zhinan-2024.2.29.0.dist-info/WHEEL
apache_mina_2_yonghu_zhinan-2024.2.29.0.dist-info/entry_points.txt
apache_mina_2_yonghu_zhinan-2024.2.29.0.dist-info/top_level.txt
apache_mina_2_yonghu_zhinan-2024.2.29.0.dist-info/RECORD
